kubernetes_provider/__init__.py
kubernetes_provider/client.py
kubernetes_provider/py.typed
kubernetes_provider/resources/__init__.py
kubernetes_provider/resources/configmap.py
kubernetes_provider/resources/secret.py
kubernetes_provider/resources/service.py
kubernetes_provider/resources/statefulset.py
pragmatiks_kubernetes_provider-0.2.0.dist-info/WHEEL
pragmatiks_kubernetes_provider-0.2.0.dist-info/METADATA
pragmatiks_kubernetes_provider-0.2.0.dist-info/RECORD
