Metadata-Version: 2.3
Name: pragmatiks-kubernetes-provider
Version: 0.2.0
Summary: Generic Kubernetes resources using lightkube
Author: Pragmatiks
Author-email: Pragmatiks <team@pragmatiks.io>
Requires-Dist: pragmatiks-sdk>=0.6.0
Requires-Dist: pragmatiks-gcp-provider>=0.55.0
Requires-Dist: lightkube>=0.15.0
Requires-Dist: google-auth>=2.30.0
Requires-Dist: requests>=2.32.0
Requires-Python: >=3.13
